hyperdiary/__init__.py
hyperdiary/__main__.py
hyperdiary/check.py
hyperdiary/diary.py
hyperdiary/html.py
hyperdiary/htmltags.py
hyperdiary/hugo.py
hyperdiary/localization.py
hyperdiary/simplepath.py
hyperdiary/stats.py
hyperdiary/tiddlywiki.py
hyperdiary/view.py
hyperdiary/assets/css/picnic.min.css
hyperdiary-0.7.0.data/data/hyperdiary/assets/css/picnic.min.css
tests/__init__.py
tests/test_doctests.py
tests/test_hyperdiary.py
tests/src/hyperdiary.json
tests/src/2019/05.yaml
tests/src/2019/05_bad_entries.yaml
tests/src/2019/06.yaml
hyperdiary-0.7.0.dist-info/AUTHORS.rst
hyperdiary-0.7.0.dist-info/LICENSE
hyperdiary-0.7.0.dist-info/METADATA
hyperdiary-0.7.0.dist-info/WHEEL
hyperdiary-0.7.0.dist-info/entry_points.txt
hyperdiary-0.7.0.dist-info/top_level.txt
hyperdiary-0.7.0.dist-info/RECORD
