Metadata-Version: 2.1
Name: hyperdiary
Version: 0.7.0
Summary: A command line tool for my image processing needs.
Home-page: https://github.com/luphord/hyperdiary
Author: luphord
Author-email: luphord@protonmail.com
License: MIT license
Keywords: hyperdiary
Classifier: Development Status :: 3 - Alpha
Classifier: Intended Audience :: Developers
Classifier: License :: OSI Approved :: MIT License
Classifier: Natural Language :: English
Classifier: Programming Language :: Python :: 3
Classifier: Programming Language :: Python :: 3.8
Classifier: Programming Language :: Python :: 3.9
Classifier: Programming Language :: Python :: 3.10
Classifier: Programming Language :: Python :: 3.11
Classifier: Programming Language :: Python :: 3.12
License-File: LICENSE
License-File: AUTHORS.rst
Requires-Dist: PyYAML >=6.0
Requires-Dist: colorama >=0.4.6
